combidata/__init__.py
combidata/classes/__init__.py
combidata/classes/case.py
combidata/classes/combination.py
combidata/classes/data_generator.py
combidata/classes/process.py
combidata/processes/__init__.py
combidata/processes/combine.py
combidata/processes/form.py
combidata/processes/genetate.py
combidata-0.2.2.4.dist-info/LICENSE
combidata-0.2.2.4.dist-info/METADATA
combidata-0.2.2.4.dist-info/WHEEL
combidata-0.2.2.4.dist-info/top_level.txt
combidata-0.2.2.4.dist-info/RECORD
