Metadata-Version: 2.1
Name: combidata
Version: 0.2.2.4
Summary: Package for random data generation, combination and data prepare for tests
Home-page: https://github.com/Warrfie/combidata
Author: Kuklikov Maxim (Warrfie)
Author-email: "MaximKuklikov(Warrfie)" <warrfie@gmail.com>
Project-URL: Homepage, https://github.com/Warrfie/combidata
Keywords: QA,SET,random data generation,testing API,testing,autotesting
Classifier: Development Status :: 4 - Beta
Classifier: Intended Audience :: Information Technology
Classifier: Topic :: Software Development :: Quality Assurance
Classifier: License :: OSI Approved :: MIT License
Classifier: Programming Language :: Python :: 3
Requires-Python: >=3.10, <4
License-File: LICENSE
